rtl/r_sync.sv
module r_sync (clk, resetn, data_in, detect_add, full_0, full_1, full_2, full_3, empty_0, empty_1, empty_2, empty_3, write_enb_reg, read_enb_0, read_enb_1, read_enb_2, read_enb_3,
                write_enb, fifo_full, vld_out_0, vld_out_1, vld_out_2, vld_out_3, soft_reset_0, soft_reset_1, soft_reset_2, soft_reset_3);
            
            input [1:0] data_in;
            input clk, resetn, detect_add;
            input full_0, full_1, full_2, full_3, empty_0, empty_1, empty_2, empty_3;
            input write_enb_reg, read_enb_0, read_enb_1, read_enb_2, read_enb_3;

            output reg [3:0] write_enb;
            output reg fifo_full;
            output reg vld_out_0, vld_out_1, vld_out_2, vld_out_3;
            output reg soft_reset_0, soft_reset_1, soft_reset_2, soft_reset_3;

            reg [1:0] data_temp;
            reg [4:0] soft_rst_count_0, soft_rst_count_1, soft_rst_count_2, soft_rst_count_3;

            //======================== FIFO FULL LGOIC ========================//


            always@(posedge clk) begin
                if(~resetn) begin
                    data_temp <= 'b0;
                end
                else begin
                    data_temp <= data_in;
                end
            end

            always @(posedge clk) begin
                if(~resetn) begin
                    fifo_full <= 1'b0;
                end

                else begin
                    if(detect_add) begin
                        
                        case(data_temp)

                            2'b00: begin
                                fifo_full <= full_0;

                                if(write_enb_reg) begin
                                    write_enb <= 4'b0001;
                                end                      
                                else begin
                                    write_enb <= 'b0;
                                end      
                            end 

                            2'b01: begin
                                fifo_full <= full_1;

                                if(write_enb_reg) begin
                                    write_enb <= 4'b0010;
                                end                      
                                else begin
                                    write_enb <= 'b0;
                                end      
                            end

                            2'b10: begin
                                fifo_full <= full_2;

                                if(write_enb_reg) begin
                                    write_enb <= 4'b0100;
                                end                      
                                else begin
                                    write_enb <= 'b0;
                                end      
                            end

                            2'b11: begin
                                fifo_full <= full_3;

                                if(write_enb_reg) begin
                                    write_enb <= 4'b1000;
                                end                      
                                else begin
                                    write_enb <= 'b0;
                                end      
                            end

                        endcase

                    end
                end
            end


            //=================================================================//





            //======================== SOFT RESET LGOIC ========================//

            
            always@(posedge clk) begin
                if(~resetn) begin
                    soft_reset_0 <= 1'b0;
                end

                else if(vld_out_0) begin
                        if(~read_enb_0) begin
                            if(soft_rst_count_0 == 29) begin
                                soft_reset_0 <= 1'b1;
                                soft_rst_count_0 <= 'd0;
                            end

                            else begin
                                soft_reset_0 <= 1'b0;
                                soft_rst_count_0 <= soft_rst_count_0 + 1;
                            end
                        end

                        else begin
                                soft_reset_0 <= 1'b0;
                                soft_rst_count_0 <= 'd0;
                        end
                end 
            end



            always@(posedge clk) begin
                if(~resetn) begin
                    soft_reset_1 <= 1'b0;
                end

                else if(vld_out_1) begin
                        if(~read_enb_1) begin
                            if(soft_rst_count_1 == 29) begin
                                soft_reset_1 <= 1'b1;
                                soft_rst_count_1 <= 'd0;
                            end

                            else begin
                                soft_reset_1 <= 1'b0;
                                soft_rst_count_1 <= soft_rst_count_1 + 1;
                            end
                        end

                        else begin
                                soft_reset_1 <= 1'b0;
                                soft_rst_count_1 <= 'd0;
                        end
                end 
            end


            always@(posedge clk) begin
                if(~resetn) begin
                    soft_reset_2 <= 1'b0;
                end

                else if(vld_out_2) begin
                        if(~read_enb_2) begin
                            if(soft_rst_count_2 == 29) begin
                                soft_reset_2 <= 1'b1;
                                soft_rst_count_2 <= 'd0;
                            end

                            else begin
                                soft_reset_2 <= 1'b0;
                                soft_rst_count_2 <= soft_rst_count_2 + 1;
                            end
                        end

                        else begin
                                soft_reset_2 <= 1'b0;
                                soft_rst_count_2 <= 'd0;
                        end
                end 
            end

            always@(posedge clk) begin
                if(~resetn) begin
                    soft_reset_3 <= 1'b0;
                end

                else if(vld_out_3) begin
                        if(~read_enb_3) begin
                            if(soft_rst_count_3 == 29) begin
                                soft_reset_3 <= 1'b1;
                                soft_rst_count_3 <= 'd0;
                            end

                            else begin
                                soft_reset_3 <= 1'b0;
                                soft_rst_count_3 <= soft_rst_count_3 + 1;
                            end
                        end

                        else begin
                                soft_reset_3 <= 1'b0;
                                soft_rst_count_3 <= 'd0;
                        end
                end 
            end


            //=================================================================//


            //======================== VLD_OUT LGOIC ========================//


            assign vld_out_0 = ~empty_0;
            assign vld_out_1 = ~empty_1;
            assign vld_out_2 = ~empty_2;
            assign vld_out_3 = ~empty_3;



endmodule

src/tb/r_sync_tb.sv
module r_sync_tb();

    reg [1:0] data_in;
    reg clk, resetn, detect_add;
    reg full_0, full_1, full_2, full_3, empty_0, empty_1, empty_2, empty_3;
    reg write_enb_reg, read_enb_0, read_enb_1, read_enb_2, read_enb_3;

    wire [3:0] write_enb;
    wire fifo_full;
    wire vld_out_0, vld_out_1, vld_out_2, vld_out_3;
    wire soft_reset_0, soft_reset_1, soft_reset_2, soft_reset_3;



    r_sync dut (clk, resetn, data_in, detect_add, full_0, full_1, full_2, full_3, empty_0, empty_1, empty_2, empty_3, write_enb_reg, read_enb_0, read_enb_1, read_enb_2, read_enb_3, write_enb, fifo_full, vld_out_0, vld_out_1, vld_out_2, vld_out_3, soft_reset_0, soft_reset_1, soft_reset_2, soft_reset_3);
    
    //router_sync dut(clk, resetn, data_in, detect_add, full_0,full_1,full_2, empty_0,empty_1,empty_2, write_enb_reg, read_enb_0,read_enb_1,read_enb_2,write_enb, fifo_full, vld_out_0,vld_out_1,vld_out_2, soft_reset_0,soft_reset_1,soft_reset_2);

    always begin
        #5 clk = 1'b1;
        #5 clk = ~clk;
    end

    task reset();
        @(negedge clk);
        resetn = 1'b0;
        #20;
        @(negedge clk);
        resetn = 1'b1;
    endtask


    task vld_out();
        @(negedge clk);
            empty_0 = 1;
        #100;
        @(negedge clk);
            empty_0 = 0;
        

        @(negedge clk);
            empty_1 = 1;
        #100;
        @(negedge clk);
            empty_1 = 0;


        @(negedge clk);
            empty_2 = 1;      
        #50;
        @(negedge clk);
            empty_2 = 0;


        @(negedge clk);

            empty_3 = 1;        
        #90;
            empty_3 = 0;

    endtask

    task write_enable();
        
        @(negedge clk);
        detect_add <= 1;
        @(negedge clk);
        full_0 <= 1'b1;
        @(negedge clk);
        data_in <= 2'b00;
        @(negedge clk);
        write_enb_reg <= 1'b1;


        @(negedge clk);
        data_in <= 2'b01;
        @(negedge clk);
        detect_add <= 1;
        @(negedge clk);
        full_1 <= 1'b1;
        @(negedge clk);
        data_in <= 2'b01;
        @(negedge clk);
        write_enb_reg <= 1'b1;

        #100;
        @(negedge clk);
        detect_add <= 1;
        @(negedge clk);
        full_3 <= 1'b1;
        @(negedge clk);
        data_in <= 2'b11;
        @(negedge clk);
        write_enb_reg <= 1'b1;

        #100;

        @(negedge clk);
        detect_add <= 1;
        @(negedge clk);
        full_2 <= 1'b1;
        @(negedge clk);
        data_in <= 2'b10;
        @(negedge clk);
        write_enb_reg <= 1'b1;
    endtask

    task soft_rst();
        @(negedge clk);
        empty_0 = 0;
        repeat(20) begin
            @(negedge clk) read_enb_0 = 0;
        end
    
        @(negedge clk);
        read_enb_0 = 1;
        @(negedge clk);
        empty_0 = 1;


        #50;

        @(negedge clk);
        empty_1 = 0;
        repeat(20) begin
            @(negedge clk) read_enb_1 = 0;
        end
    
        @(negedge clk);
        read_enb_1 = 1;
        @(negedge clk);
        empty_1 = 1;

        #50;

        @(negedge clk);
        empty_2 = 0;
        repeat(20) begin
            @(negedge clk) read_enb_2 = 0;
        end
    
        @(negedge clk);
        read_enb_2 = 1;
        @(negedge clk);
        empty_2 = 1;


        #50;

        @(negedge clk);
        empty_3 = 0;
        repeat(20) begin
            @(negedge clk) read_enb_3 = 0;
        end
    
        @(negedge clk);
        read_enb_3 = 1;
        @(negedge clk);
        empty_3 = 1;

    endtask



    initial begin
        reset();
        #5;

        vld_out();
        #5;
        reset();
        #5;
        write_enable();

        #10;

        soft_rst();

        #20;
        
        reset();

    end


    initial begin
        $dumpfile("sync_wave.vcd");
        $dumpvars();
        $monitor(dut.data_temp, dut.detect_add);
        $monitor("LOLOLOLOL",write_enb, dut.write_enb);

        #80000 $finish();
    end

endmodule

src/sync_wave.vcd
$date
	Fri Mar 03 14:22:03 2023
$end
$version
	QuestaSim Version 10.6c
$end
$timescale
	1ns
$end

$scope module r_sync_tb $end

$scope task reset $end
$upscope $end

$scope task vld_out $end
$upscope $end

$scope task write_enable $end
$upscope $end

$scope task soft_rst $end
$upscope $end

$scope module dut $end
$var wire 1 ! detect_add $end
$var reg 4 " write_enb [3:0] $end
$var reg 2 # data_temp [1:0] $end
$upscope $end
$upscope $end

$scope begin std $end
$upscope $end
$enddefinitions $end
#0
$dumpvars
bx "
bx #
x!
$end
#15
b0 #
b0 "
#450
1!
#455
bx #
#475
b0 #
#480
b1 "
#495
b1 #
b10 "
#655
b11 #
b1000 "
#785
b10 #
b100 "
#1855
b0 #
b1 "
#1875
b10 #
b100 "
